{
  "delay": {
    "SPI": {
      "speed_hz": "list(set(list(range(10000, 8000001, 1000)) + [10000, 14400, 19200, 28800, 38400, 57600, 115200]))",
      "script_name": "delay.py",
      "receiver_src_name": {
        "Arduino_UNO": "Delay.ino",
        "ESP32-DevKitC": "Delay.c"
      }
    },
    "I2C": {
      "speed_hz": "list(set(list(range(10000, 500001, 1000)) + [10000, 14400, 19200, 28800, 38400, 57600, 115200]))",
      "script_name": "delay.py",
      "receiver_src_name": {
        "Arduino_UNO": "Delay.ino",
        "ESP32-DevKitC": "Delay.c"
      }
    },
    "UART": {
      "speed_hz": "list(set(list(range(10000, 8000001, 1000)) + [10000, 14400, 19200, 28800, 38400, 57600, 115200]))",
      "script_name": "delay.py",
      "receiver_src_name": {
        "Arduino_UNO": "Delay.ino",
        "ESP32-DevKitC": "delay.c"
      }
    }
  },

  "throughput": {
    "SPI": {
      "speed_hz": "list(set(list(range(10000, 8000001, 1000)) + [10000, 14400, 19200, 28800, 38400, 57600, 115200]))",
      "script_name": "throughput.py",
      "receiver_src_name": {
        "Arduino_UNO": "Throughput.ino",
        "ESP32-DevKitC": "Throughput.ino"
      }
    },
    "I2C": {
      "speed_hz": "list(set(list(range(10000, 500001, 1000)) + [10000, 14400, 19200, 28800, 38400, 57600, 115200]))",
      "script_name": "throughput.py",
      "receiver_src_name": {
        "Arduino_UNO": "Throughput.ino",
        "ESP32-DevKitC": "Throughput.c"
      }
    },
    "UART": {
      "speed_hz": "list(set(list(range(10000, 8000001, 1000)) + [10000, 14400, 19200, 28800, 38400, 57600, 115200]))",
      "script_name": "throughput.py",
      "receiver_src_name": {
        "Arduino_UNO": "Throughput.ino",
        "ESP32-DevKitC": "Throughput.ino"
      }
    }
  },

  "proc_time": {
    "I2C": {
      "speed_hz": "list(set(list(range(10000, 500001, 1000)) + [10000, 14400, 19200, 28800, 38400, 57600, 115200]))",
      "script_name": "proc_time.py",
      "receiver_src_name": {
        "Arduino_UNO": "ProcTime.ino",
        "ESP32-DevKitC": "ProcTime.c"
      }
    }
  }
}